stream/__init__.py
stream/dataset.py
stream/stream.py
v_stream-0.1.2.dist-info/METADATA
v_stream-0.1.2.dist-info/WHEEL
v_stream-0.1.2.dist-info/top_level.txt
v_stream-0.1.2.dist-info/RECORD
